lowhass/__init__.py
lowhass/rest_client.py
lowhass/util.py
lowhass/ws_client.py
lowhass/typings/__init__.py
lowhass/typings/config.py
lowhass/typings/events.py
lowhass/typings/service.py
lowhass/typings/state.py
lowhass/typings/status.py
lowhass-0.1.1.dist-info/LICENSE
lowhass-0.1.1.dist-info/METADATA
lowhass-0.1.1.dist-info/WHEEL
lowhass-0.1.1.dist-info/top_level.txt
lowhass-0.1.1.dist-info/RECORD
